src/mcp_python/__init__.py
src/mcp_python/__main__.py
src/mcp_python/server.py
orange_mcp_python-0.1.4.dist-info/METADATA
orange_mcp_python-0.1.4.dist-info/WHEEL
orange_mcp_python-0.1.4.dist-info/entry_points.txt
orange_mcp_python-0.1.4.dist-info/licenses/LICENSE
orange_mcp_python-0.1.4.dist-info/RECORD
