Metadata-Version: 2.4
Name: orange-mcp-python
Version: 0.1.4
Summary: MCP server providing a Python REPL with persistent session
Project-URL: Homepage, https://github.com/piplin-es/mcp-python
Project-URL: Repository, https://github.com/piplin-es/mcp-python.git
Project-URL: Issues, https://github.com/piplin-es/mcp-python/issues
Project-URL: Github, https://github.com/piplin-es/mcp-python
Author-email: Tynan Daly <tynan@hdr.is>
License-Expression: MIT
License-File: LICENSE
Keywords: mcp,python,repl,server
Classifier: Development Status :: 4 - Beta
Classifier: License :: OSI Approved :: MIT License
Classifier: Operating System :: OS Independent
Classifier: Programming Language :: Python :: 3
Classifier: Programming Language :: Python :: 3.10
Classifier: Programming Language :: Python :: 3.11
Classifier: Programming Language :: Python :: 3.12
Requires-Python: >=3.10
Requires-Dist: llm-parser-filter
Requires-Dist: mcp
Requires-Dist: mcp-gsuite
Requires-Dist: python-dotenv
